VirtualPatient_env/__init__.py
VirtualPatient_env/envs/__init__.py
VirtualPatient_env-0.0.1.dist-info/METADATA
VirtualPatient_env-0.0.1.dist-info/WHEEL
VirtualPatient_env-0.0.1.dist-info/top_level.txt
VirtualPatient_env-0.0.1.dist-info/RECORD
