Metadata-Version: 2.1
Name: VirtualPatient-env
Version: 0.0.1
Summary: A Gym Env for 'VirtualPatient' project
Requires-Dist: gym
